tessa_sdk/__init__.py
tessa_sdk/async_client.py
tessa_sdk/browser.py
tessa_sdk/exceptions.py
tessa_sdk/models.py
tessa_sdk/py.typed
tessa_sdk/sync_client.py
tessa_sdk-0.1.0.dist-info/licenses/LICENSE
tessa_sdk-0.1.0.dist-info/METADATA
tessa_sdk-0.1.0.dist-info/WHEEL
tessa_sdk-0.1.0.dist-info/top_level.txt
tessa_sdk-0.1.0.dist-info/RECORD
