Metadata-Version: 2.4
Name: tessa_sdk
Version: 0.1.0
Summary: Python SDK for the Tessa Browser Agent & Workflows API
Home-page: https://github.com/GeneralAgencyAI/tessa_sdk
Author: Tessa Team
Author-email: Tessa Team <support@generalagency.ai>
Maintainer-email: Tessa Team <support@generalagency.ai>
License: MIT
Project-URL: Homepage, https://heytessa.ai
Project-URL: Documentation, https://docs.heytessa.ai
Project-URL: Repository, https://github.com/GeneralAgencyAI/tessa_sdk
Project-URL: Issues, https://github.com/GeneralAgencyAI/tessa_sdk/issues
Classifier: Development Status :: 4 - Beta
Classifier: Intended Audience :: Developers
Classifier: License :: OSI Approved :: MIT License
Classifier: Programming Language :: Python :: 3
Classifier: Programming Language :: Python :: 3.8
Classifier: Programming Language :: Python :: 3.9
Classifier: Programming Language :: Python :: 3.10
Classifier: Programming Language :: Python :: 3.11
Classifier: Programming Language :: Python :: 3.12
Classifier: Programming Language :: Python :: 3.13
Classifier: Topic :: Software Development :: Libraries :: Python Modules
Classifier: Topic :: Internet :: WWW/HTTP
Requires-Python: >=3.8
License-File: LICENSE
Requires-Dist: httpx>=0.25.0
Requires-Dist: pydantic>=2.0.0
Requires-Dist: python-dotenv>=1.0.0
Requires-Dist: typing-extensions>=4.5.0; python_version < "3.10"
Provides-Extra: dev
Requires-Dist: pytest>=7.0.0; extra == "dev"
Requires-Dist: pytest-asyncio>=0.21.0; extra == "dev"
Requires-Dist: pytest-cov>=4.0.0; extra == "dev"
Requires-Dist: black>=23.0.0; extra == "dev"
Requires-Dist: ruff>=0.1.0; extra == "dev"
Requires-Dist: mypy>=1.0.0; extra == "dev"
Requires-Dist: pre-commit>=3.0.0; extra == "dev"
Dynamic: author
Dynamic: home-page
Dynamic: license-file
Dynamic: requires-python
